manim_chessrender/__init__.py
manim_chessrender/images/black-bishop.ico
manim_chessrender/images/black-king.ico
manim_chessrender/images/black-knight.ico
manim_chessrender/images/black-pawn.ico
manim_chessrender/images/black-queen.ico
manim_chessrender/images/black-rook.ico
manim_chessrender/images/white-bishop.ico
manim_chessrender/images/white-king.ico
manim_chessrender/images/white-knight.ico
manim_chessrender/images/white-pawn.ico
manim_chessrender/images/white-queen.ico
manim_chessrender/images/white-rook.ico
manim_chessrender/mobjects/chess_cli.py
manim_chessrender/mobjects/chessboard.py
manim_chessrender-0.1.1.dist-info/LICENSE
manim_chessrender-0.1.1.dist-info/METADATA
manim_chessrender-0.1.1.dist-info/WHEEL
manim_chessrender-0.1.1.dist-info/entry_points.txt
manim_chessrender-0.1.1.dist-info/RECORD
