Metadata-Version: 2.1
Name: manim-chessrender
Version: 0.1.1
Summary: A Manim plugin that allows you to generate scenes with chessboards with minimal setup.
Author: codevardhan
Author-email: harsha7vardhan@gmail.com
Requires-Python: >=3.10,<4.0
Classifier: Programming Language :: Python :: 3
Classifier: Programming Language :: Python :: 3.10
Classifier: Programming Language :: Python :: 3.11
Classifier: Programming Language :: Python :: 3.12
